{
  "audit_mode": "source_provenance_seed",
  "source_pdf_sha256": "b9bfff9b8873262e421d291b2f3ef6e050e740645b6afd51c40fbe380051946f",
  "source_pdf_path": "data/raw/pdfs/GF_Aframe_Recreation-0526.pdf",
  "model": "source_provenance_visual_seed_v1",
  "prompt_version": "disney-pdf-visual-audit-v1",
  "audited_at": "2026-06-27T03:48:39.499505+00:00",
  "activities": [
    {
      "title": "Arcadia Games",
      "section": "Resort Activities",
      "date_text": "fy26-q2-0526",
      "schedule_text": "Daily from 8:00am-11:00pm",
      "location": "Arcadia Games",
      "description": "Play the latest and greatest family-friendly video games.",
      "price_state": "fee",
      "price_evidence": "none",
      "optional_price_options": [],
      "bbox": {
        "page": 1,
        "x": 911.0,
        "y": 519.0,
        "width": 430.5,
        "height": 31.5
      },
      "confidence": "medium",
      "row_key": "grand-floridian:arcadia-games"
    },
    {
      "title": "Cabana Rentals",
      "section": "Resort Activities",
      "date_text": "fy26-q2-0526",
      "schedule_text": "Daily from 10:00am-7:00pm",
      "location": "Cabana Rentals",
      "description": "To book, call 407-WWDW-PLAY or see a Recreation",
      "price_state": "fee",
      "price_evidence": "none",
      "optional_price_options": [],
      "bbox": {
        "page": 1,
        "x": 912.0,
        "y": 677.5,
        "width": 458.5,
        "height": 31.5
      },
      "confidence": "medium",
      "row_key": "grand-floridian:cabana-rentals"
    },
    {
      "title": "Captain’s Shipyard Boat Rentals",
      "section": "Resort Activities",
      "date_text": "fy26-q2-0526",
      "schedule_text": "Daily from 11:00am-5:00pm",
      "location": "Captain’s Shipyard Boat Rentals",
      "description": "",
      "price_state": "fee",
      "price_evidence": "none",
      "optional_price_options": [],
      "bbox": {
        "page": 1,
        "x": 912.0,
        "y": 877.0,
        "width": 448.0,
        "height": 26.0
      },
      "confidence": "medium",
      "row_key": "grand-floridian:captains-shipyard-boat-rentals"
    },
    {
      "title": "Cheshire Challenges",
      "section": "Resort Activities",
      "date_text": "fy26-q2-0526",
      "schedule_text": "Daily at 12:30pm",
      "location": "Beach Pool Deck",
      "description": "Join us for a game by the Beach Pool.",
      "price_state": "free",
      "price_evidence": "marker_absent_under_legend",
      "optional_price_options": [],
      "bbox": {
        "page": 1,
        "x": 912.0,
        "y": 1035.5,
        "width": 502.5,
        "height": 25.5
      },
      "confidence": "medium",
      "row_key": "grand-floridian:cheshire-challenges"
    },
    {
      "title": "Health Club",
      "section": "Resort Activities",
      "date_text": "fy26-q2-0526",
      "schedule_text": "Open 24 hours a day, 7 days a week",
      "location": "The Grand Floridian Spa",
      "description": "Continue pushing towards your wellness goals in our full-service fitness center",
      "price_state": "free",
      "price_evidence": "marker_absent_under_legend",
      "optional_price_options": [],
      "bbox": {
        "page": 1,
        "x": 160.0,
        "y": 1176.0,
        "width": 285.0,
        "height": 25.5
      },
      "confidence": "medium",
      "row_key": "grand-floridian:health-club"
    },
    {
      "title": "Movie Under the Stars",
      "section": "Movie Under the Stars",
      "date_text": "fy26-q2-0526",
      "schedule_text": "Courtyard Lawn | 8:00PM",
      "location": "Courtyard Lawn",
      "description": "",
      "price_state": "free",
      "price_evidence": "marker_absent_under_legend",
      "optional_price_options": [],
      "bbox": {
        "page": 1,
        "x": 116.5,
        "y": 1471.0,
        "width": 670.0,
        "height": 28.5
      },
      "confidence": "medium",
      "row_key": "grand-floridian:movie-under-the-stars"
    },
    {
      "title": "Arts & Crafts",
      "section": "Resort Activities",
      "date_text": "fy26-q2-0526",
      "schedule_text": "From 3:00pm-4:00pm",
      "location": "Beach Pool Deck",
      "description": "Sunday, Monday, Wednesday, Friday and Tuesday and Thursday................. Design Your Own Tumblers",
      "price_state": "fee",
      "price_evidence": "none",
      "optional_price_options": [],
      "bbox": {
        "page": 1,
        "x": 911.0,
        "y": 1509.0,
        "width": 408.5,
        "height": 32.0
      },
      "confidence": "medium",
      "row_key": "grand-floridian:arts-crafts"
    },
    {
      "title": "Campfire",
      "section": "Resort Activities",
      "date_text": "fy26-q2-0526",
      "schedule_text": "Nightly from 5:30pm-6:30pm",
      "location": "Near Beach Pool",
      "description": "Enjoy the warm glow of the campfire with complimentary marshmallows. S’mores kits available for purchase.",
      "price_state": "free",
      "price_evidence": "marker_absent_under_legend",
      "optional_price_options": [
        {
          "optionName": "Mickey S'mores Kit",
          "priceBasis": "optional_add_on",
          "priceCentsMin": 700,
          "priceCentsMax": 700,
          "priceConfidence": "secondary_verified",
          "verificationStatus": "needs_disney_confirmation",
          "sourceUrl": "https://chipandco.com/cute-tour-humphreys-hideout-wilderness-lodge-631738/",
          "sourceLabel": "Chip and Company Wilderness Lodge report",
          "notes": "Usually around $7 plus tax; do not present as a guaranteed Disney-published price unless Disney confirms it for the resort and period."
        }
      ],
      "bbox": {
        "page": 1,
        "x": 912.0,
        "y": 1788.0,
        "width": 210.5,
        "height": 25.5
      },
      "confidence": "medium",
      "row_key": "grand-floridian:campfire"
    },
    {
      "title": "Video Game Dance Party",
      "section": "Resort Activities",
      "date_text": "fy26-q2-0526",
      "schedule_text": "Sunday and Thursday at 7:30pm",
      "location": "Courtyard Lawn",
      "description": "Show off your best moves at this interactive dance party!",
      "price_state": "free",
      "price_evidence": "marker_absent_under_legend",
      "optional_price_options": [],
      "bbox": {
        "page": 1,
        "x": 911.0,
        "y": 2263.0,
        "width": 584.0,
        "height": 25.5
      },
      "confidence": "medium",
      "row_key": "grand-floridian:video-game-dance-party"
    }
  ],
  "warnings": [
    "seeded_from_gold_field_provenance_not_independent_gpt_visual_review"
  ]
}
